pygdrive/__init__.py
pygdrive/gdrive.py
pygdrive/tests/__init__.py
pygdrive/tests/test_drive.py
pygdrive-1.0.1.dist-info/LICENSE.txt
pygdrive-1.0.1.dist-info/METADATA
pygdrive-1.0.1.dist-info/WHEEL
pygdrive-1.0.1.dist-info/top_level.txt
pygdrive-1.0.1.dist-info/RECORD
