Metadata-Version: 2.1
Name: pygdrive
Version: 1.0.1
Summary: Google Drive API for service accounts
Home-page: https://github.com/vectorspace-ai/pygdrive
Author: Vectorspace AI
Author-email: arina@vectorspace.ai
License: LICENSE
Platform: UNKNOWN
Requires-Dist: google-api-python-client (>=2.1.0)
Requires-Dist: google-auth-httplib2 (>=0.1.0)
Requires-Dist: google-auth-oauthlib (>=0.4.4)
